[
  {
    "name": "Basic",
    "slug": "basic",
    "benefits": [
      "Access to newbie level",
      "Publish up to 3 projects",
      "Discuss in community forum",
      "Suitable for your who just want to try out with community support"
    ],
    "price": {
      "cost": 0,
      "info": "Forever"
    },
    "buttons": {
      "isNotAuthenticated": {
        "href": "/signup",
        "text": "Sign Up for Basic"
      },
      "isAuthenticated": {
        "href": "/dashboard/overview",
        "text": "Continue Basic"
      }
    }
  },
  {
    "name": "Pro",
    "slug": "pro",
    "benefits": [
      "Everything in Basic",
      "Access to learn all levels",
      "Publish unlimited projects",
      "Suitable for you who want to learn and practice more with priority support"
    ],
    "price": {
      "cost": 10,
      "info": "month"
    },
    "buttons": {
      "isNotAuthenticated": {
        "href": "/signup?plan=pro",
        "text": "Sign Up for Pro"
      },
      "isAuthenticated": {
        "href": "/settings/billing?plan=pro",
        "text": "Subscribe Pro"
      }
    }
  },
  {
    "name": "Super",
    "slug": "super",
    "benefits": [
      "Everything in Basic and Pro",
      "Lifetime Pro benefits",
      "Dedicated private 1-on-1 mentorship sessions with real dedicated mentor for 150 hours",
      "Suitable for you who want to get real serious on getting a professional job, freelancing, upgrading your career, or building a tech business"
    ],
    "price": {
      "cost": 2000,
      "info": "1 person"
    },
    "buttons": {
      "isNotAuthenticated": {
        "href": "/signup?plan=super",
        "text": "Sign Up for Super"
      },
      "isAuthenticated": {
        "href": "/settings/billing?plan=super",
        "text": "Request Super"
      }
    }
  }
]
